{
  "collectionName": "components_homepage_hero5s",
  "info": {
    "displayName": "hero5",
    "icon": "cube",
    "description": ""
  },
  "options": {},
  "attributes": {
    "hero5Image": {
      "type": "media",
      "multiple": false,
      "required": false,
      "allowedTypes": [
        "images",
        "files",
        "videos",
        "audios"
      ]
    },
    "hero5label1": {
      "type": "string"
    },
    "hero5label2": {
      "type": "string"
    },
    "hero5ImageMobile": {
      "allowedTypes": [
        "images",
        "files",
        "videos",
        "audios"
      ],
      "type": "media",
      "multiple": false
    }
  }
}
